README.md
setup.py
./servicecatalog/__init__.py
./servicecatalog/_version.py
servicecatalog.egg-info/PKG-INFO
servicecatalog.egg-info/SOURCES.txt
servicecatalog.egg-info/dependency_links.txt
servicecatalog.egg-info/requires.txt
servicecatalog.egg-info/top_level.txt
servicecatalog.egg-info/zip-safe