Metadata-Version: 1.1
Name: servicecatalog
Version: 1.0.0
Summary: Provides a simple dict-based interface to Consul's service discovery.
Home-page: https://github.com/madedotcom/servicecatalog
Author: Bob Gregory
Author-email: bob@made.com
License: MIT
Platform: any
Classifier: Development Status :: 5 - Production/Stable
Classifier: Intended Audience :: Developers
Classifier: License :: OSI Approved :: MIT License
Classifier: Operating System :: POSIX
Classifier: Programming Language :: Python :: 3
